hyper_sh/__init__.py
hyper_sh/requests_aws4auth/__init__.py
hyper_sh/requests_aws4auth/aws4auth.py
hyper_sh/requests_aws4auth/aws4signingkey.py
hyper_sh/requests_aws4auth/exceptions.py
hyper_sh/requests_aws4auth/service_parameters.py
hyper_sh/requests_aws4auth/six.py
hyper_sh-1.0.7.dist-info/DESCRIPTION.rst
hyper_sh-1.0.7.dist-info/METADATA
hyper_sh-1.0.7.dist-info/RECORD
hyper_sh-1.0.7.dist-info/WHEEL
hyper_sh-1.0.7.dist-info/metadata.json
hyper_sh-1.0.7.dist-info/pbr.json
hyper_sh-1.0.7.dist-info/top_level.txt
