Metadata-Version: 2.0
Name: hyper-sh
Version: 1.0.7
Summary: docker-py on hyper infra
Home-page: https://github.com/tardyp/hyper_sh
Author: Pierre Tardy
Author-email: tardyp@gmail.com
License: MIT
Keywords: docker
Requires-Dist: docker-py
